data_flow_s3_import/__init__.py
data_flow_s3_import/ingest.py
data_flow_s3_import/models.py
data_flow_s3_import/py.typed
data_flow_s3_import/tests/__init__.py
data_flow_s3_import/tests/settings.py
data_flow_s3_import/tests/test_ingest.py
data_flow_s3_import/tests/test_ingest_to_model.py
data_flow_s3_import/tests/utils.py
data_flow_s3_import/types.py
data_flow_s3_import-0.1.0.dist-info/LICENSE
data_flow_s3_import-0.1.0.dist-info/METADATA
data_flow_s3_import-0.1.0.dist-info/WHEEL
data_flow_s3_import-0.1.0.dist-info/RECORD
