Metadata-Version: 2.1
Name: data-flow-s3-import
Version: 0.1.0
Summary: Helps Python and Django projects import data exposed by Data Flow into a S3 bucket
Home-page: https://github.com/uktrade/data-flow-s3-import
License: MIT
Author: Alsen Aligullu
Author-email: alsen.aligullu@digitial.trade.gov.uk
Requires-Python: >=3.12,<4.0
Classifier: License :: OSI Approved :: MIT License
Classifier: Programming Language :: Python :: 3
Classifier: Programming Language :: Python :: 3.12
Requires-Dist: boto3 (>=1.35.49,<2.0.0)
Requires-Dist: django (>=5.1,<6.0)
Requires-Dist: smart-open (>=7.1.0,<8.0.0)
